{"code": 26, "message": "Valid method.", "result": {"0": {"model_info": [{"id": 5179, "noteb_name": "Apple MacBook Air  M1 20. (US)", "name": "Apple MacBook Air", "extra_name": " (M1)", "submodel_info": [" M1 20.", "(US)"]}], "config_id": "4498475920383018001", "model_resources": {"thumbnail": "https://noteb.com/res/img/models/thumb/t_3121_1.jpg", "image_1": "https://noteb.com/res/img/models/3121_1.jpg", "image_2": "https://noteb.com/res/img/models/3121_2.jpg", "image_3": "https://noteb.com/res/img/models/3121_3.jpg", "image_4": "https://noteb.com/res/img/models/3121_4.jpg", "official_link": "https://www.apple.com/macbook-air/", "official_link2": null, "launch_date": "2020-11-17", "primary_model": "5179"}, "cpu": {"prod": "Arm-based", "model": "Apple M1", "lithography": "5", "cache": "16", "base_speed": "3.20", "boost_speed": "3.20", "cores": "8", "tdp": "15", "other_info": "64-bit,ARM-V,16-core Neural Engine", "rating": "52.4", "integrated_video_id": "700", "integrated_video": "Unknown"}, "display": {"size": "13.3", "horizontal_resolution": "2560", "vertical_resolution": "1600", "type": "LED IPS", "sRGB": "100", "touch": "no", "other_info": null}, "memory": {"size": "8", "speed": "3200", "type": "DDR4"}, "primary_storage": {"model": "SSD M.2 PCIe", "cap": "256", "rpm": null, "read_speed": "850"}, "secondary_storage": {"model": "N/A", "cap": "0", "rpm": null, "read_speed": null}, "gpu": {"prod": "Apple", "model": "M1 7-core", "architecture": "M1", "lithography": "5", "shaders": "112", "base_speed": "3200", "boost_speed": "3200", "shader_speed": "3200", "memory_speed": "3733", "memory_bandwidth": "64", "memory_size": "4096", "memory_type": "DDR4", "tdp": "0", "other_info": "", "rating": "9.1"}, "wireless_card": {"model": "Wi-Fi 6 AX201", "speed": "2400", "other_info": "Bluetooth 5.0,dual band,2 x antennas"}, "optical_drive": {"type": "none", "other_info": ""}, "motherboard": {"ram_slots": "soldered", "lan_card": "none", "storage_slots": "soldered", "other_info": "HD audio"}, "chassis": {"height_cm": "1.56", "height_inch": "0.61", "depth_cm": "21.24", "depth_inch": "8.36", "width_cm": "30.41", "width_inch": "11.97", "weight_kg": "1.25", "weight_lb": "2.76", "colors": "Gold,Silver,Space grey", "build_materials": "Aluminium", "peripheral_interfaces": "Thunderbolt,2 X USB-C 4.0", "video_interfaces": null, "webcam_mp": "0.920", "keyboard_type": "Backlit Chiclet keyboard", "charger": "30W (2A - 15VDC)", "other_info": "2 x speakers,Microphone array,Edgeless display,Fingerprint reader"}, "battery": {"capacity": "49.9", "cell_type": "Li-Pol", "other_info": ""}, "warranty": {"years": "1", "type_short": "Standard", "type_long": "Standard Pick-up & Return"}, "operating_system": "macOS  11.00", "config_score": "41.69", "config_price": "999", "config_price_min": "990", "config_price_max": "1009", "battery_life_raw": "9.8", "battery_life_hours": "9:45", "total_storage_capacity": "256"}}, "daily_hits_left": "837"}