{"code": 26, "message": "Valid method.", "result": {"0": {"model_info": [{"id": 5252, "noteb_name": "Asus 2-in-1 Q507IQ (US)", "name": "Asus 2-in-1 Q507IQ", "extra_name": "", "submodel_info": ["(US)"]}], "config_id": "3733413248403190151", "model_resources": {"thumbnail": "https://noteb.com/res/img/models/thumb/t_3174_1.jpg", "image_1": "https://noteb.com/res/img/models/3174_1.jpg", "image_2": "https://noteb.com/res/img/models/3174_2.jpg", "image_3": "https://noteb.com/res/img/models/3174_3.jpg", "image_4": "https://noteb.com/res/img/models/3174_4.jpg", "official_link": "https://www.asus.com/us/2-in-1-PCs/ASUS-Q507IQ/Features/", "official_link2": null, "launch_date": "2021-01-08", "primary_model": "5252"}, "cpu": {"prod": "Amd", "model": "Ryzen 7 4700U", "lithography": "7", "cache": "8", "base_speed": "2.00", "boost_speed": "4.10", "cores": "8", "tdp": "15", "other_info": "SSE4.2,AVX2.0,64-bit,AMD-V,AMD-Vi,AMD XFR,Precision Boost 2", "rating": "55.7", "integrated_video_id": "665", "integrated_video": "Unknown"}, "display": {"size": "15.6", "horizontal_resolution": "1920", "vertical_resolution": "1080", "type": "LED IPS", "sRGB": "60", "touch": "no", "other_info": null}, "memory": {"size": "8", "speed": "4266", "type": "DDR4"}, "primary_storage": {"model": "SSD M.2 PCIe", "cap": "256", "rpm": null, "read_speed": "850"}, "secondary_storage": {"model": "N/A", "cap": "0", "rpm": null, "read_speed": null}, "gpu": {"prod": "Nvidia", "model": "GeForce MX350", "architecture": "Pascal", "lithography": "14", "shaders": "384", "base_speed": "1531", "boost_speed": "1594", "shader_speed": "1531", "memory_speed": "1502", "memory_bandwidth": "64", "memory_size": "2048", "memory_type": "GDDR5", "tdp": "10", "other_info": "GPU Boost 3.0,Optimus,Nvidia PhysX,Nvidia CUDA", "rating": "14.1"}, "wireless_card": {"model": "Wi-Fi 6 AX201", "speed": "2400", "other_info": "Bluetooth 5.0,dual band,2 x antennas"}, "optical_drive": {"type": "none", "other_info": ""}, "motherboard": {"ram_slots": "soldered", "lan_card": "none", "storage_slots": " 1 X M.2 SATA/PCIe", "other_info": "HD audio"}, "chassis": {"height_cm": "1.99", "height_inch": "0.78", "depth_cm": "23.00", "depth_inch": "9.06", "width_cm": "35.70", "width_inch": "14.06", "weight_kg": "1.90", "weight_lb": "4.19", "colors": "Light grey", "build_materials": "Plastic", "peripheral_interfaces": "1 X USB-C 3.2,1 X USB 3.2,1 X USB 2.0,MicroSD card reader", "video_interfaces": "1 X HDMI", "webcam_mp": "0.920", "keyboard_type": "Backlit Chiclet keyboard", "charger": "65W (3.42A - 19VDC)", "other_info": "2 x speakers,Harman speakers,IR camera,Stylus (Optional)"}, "battery": {"capacity": "56", "cell_type": "Li-Pol", "other_info": ""}, "warranty": {"years": "1", "type_short": "Standard", "type_long": "Standard Pick-up & Return"}, "operating_system": "Windows Home 10.00", "config_score": "39.5", "config_price": "799", "config_price_min": "792", "config_price_max": "807", "battery_life_raw": "8.2", "battery_life_hours": "8:05", "total_storage_capacity": "256"}}, "daily_hits_left": "58"}